[{"title":"","cont":[{"title":"江城子·乙卯正月二十","author":"江城子·乙卯正月二十(苏轼)","url":"/shiwenv_567fcf6ffefb.aspx"},{"title":"浣溪沙·谁念西风独自","author":"浣溪沙·谁念西风独自(纳兰性德)","url":"/shiwenv_f9a34574e44a.aspx"},{"title":"离思五首·其四","author":"离思五首·其四(元稹)","url":"/shiwenv_bd4224133394.aspx"},{"title":"九歌·国殇","author":"九歌·国殇(屈原)","url":"/shiwenv_e46594efec53.aspx"},{"title":"采桑子·当时错","author":"采桑子·当时错(纳兰性德)","url":"/shiwenv_ccbd39485a6a.aspx"},{"title":"沈园二首","author":"沈园二首(陆游)","url":"/shiwenv_c69e5720e858.aspx"},{"title":"绿衣","author":"绿衣(佚名)","url":"/shiwenv_8b38b9613812.aspx"},{"title":"蝶恋花·辛苦最怜天上","author":"蝶恋花·辛苦最怜天上(纳兰性德)","url":"/shiwenv_26b87875bd77.aspx"},{"title":"遣悲怀三首·其二","author":"遣悲怀三首·其二(元稹)","url":"/shiwenv_8d7eab9265d3.aspx"},{"title":"梦微之","author":"梦微之(白居易)","url":"/shiwenv_de2ba4e71def.aspx"},{"title":"李白墓","author":"李白墓(白居易)","url":"/shiwenv_bd069c2b7711.aspx"},{"title":"山花子·风絮飘残已化","author":"山花子·风絮飘残已化(纳兰性德)","url":"/shiwenv_689770b9b1ee.aspx"},{"title":"祭十二郎文","author":"祭十二郎文(韩愈)","url":"/shiwenv_70b78cce30db.aspx"},{"title":"金缕曲·亡妇忌日有感","author":"金缕曲·亡妇忌日有感(纳兰性德)","url":"/shiwenv_459a494177cb.aspx"},{"title":"西江月·梅花","author":"西江月·梅花(苏轼)","url":"/shiwenv_ccff49f45809.aspx"},{"title":"蓼莪","author":"蓼莪(佚名)","url":"/shiwenv_e5275088809c.aspx"},{"title":"半死桐·重过阊门万事","author":"半死桐·重过阊门万事(贺铸)","url":"/shiwenv_5b5e301c1b9b.aspx"},{"title":"遣悲怀三首·其三","author":"遣悲怀三首·其三(元稹)","url":"/shiwenv_fe89b7670e0a.aspx"},{"title":"为薛台悼亡","author":"为薛台悼亡(白居易)","url":"/shiwenv_07497db4b362.aspx"},{"title":"孤雁儿·藤床纸帐朝眠","author":"孤雁儿·藤床纸帐朝眠(李清照)","url":"/shiwenv_3a838161e383.aspx"},{"title":"哭李商隐","author":"哭李商隐(崔珏)","url":"/shiwenv_465c026fba47.aspx"},{"title":"吊白居易","author":"吊白居易(李忱)","url":"/shiwenv_24e69d374b9e.aspx"},{"title":"葛生","author":"葛生(佚名)","url":"/shiwenv_b86fd2388e70.aspx"},{"title":"遣悲怀三首·其一","author":"遣悲怀三首·其一(元稹)","url":"/shiwenv_c20e02dc390a.aspx"},{"title":"黄鸟","author":"黄鸟(佚名)","url":"/shiwenv_e344fb59fa53.aspx"},{"title":"浪淘沙·帘外五更风","author":"浪淘沙·帘外五更风(李清照)","url":"/shiwenv_af698e690d11.aspx"},{"title":"南乡子·为亡妇题照","author":"南乡子·为亡妇题照(纳兰性德)","url":"/shiwenv_48e151a87687.aspx"},{"title":"思旧赋","author":"思旧赋(向秀)","url":"/shiwenv_e11fef2054ba.aspx"},{"title":"悼亡诗三首","author":"悼亡诗三首(潘安)","url":"/shiwenv_b04c1a7c4bf2.aspx"},{"title":"临江仙·送王缄","author":"临江仙·送王缄(苏轼)","url":"/shiwenv_958cd1e3c484.aspx"},{"title":"李夫人赋","author":"李夫人赋(刘彻)","url":"/shiwenv_91f8157ab013.aspx"},{"title":"莺啼序·春晚感怀","author":"莺啼序·春晚感怀(吴文英)","url":"/shiwenv_42c98cda665c.aspx"},{"title":"别房太尉墓","author":"别房太尉墓(杜甫)","url":"/shiwenv_f67ed771d1fa.aspx"},{"title":"生查子·惆怅彩云飞","author":"生查子·惆怅彩云飞(纳兰性德)","url":"/shiwenv_411ee8c83ac8.aspx"},{"title":"岳鄂王墓","author":"岳鄂王墓(赵孟頫)","url":"/shiwenv_de47f10567ee.aspx"},{"title":"木兰花慢·莺啼啼不尽","author":"木兰花慢·莺啼啼不尽(戴复古)","url":"/shiwenv_03cfdec8dfcb.aspx"},{"title":"茶瓶儿·去年相逢深院","author":"茶瓶儿·去年相逢深院(李元膺)","url":"/shiwenv_31cd3d89c124.aspx"},{"title":"醉落魄·预赏景龙门追","author":"醉落魄·预赏景龙门追(赵佶)","url":"/shiwenv_50ab8c66b566.aspx"},{"title":"青衫湿·悼亡","author":"青衫湿·悼亡(纳兰性德)","url":"/shiwenv_52e051c149d8.aspx"},{"title":"楚宫","author":"楚宫(李商隐)","url":"/shiwenv_f66b2546400c.aspx"},{"title":"沁园春·代悼亡","author":"沁园春·代悼亡(纳兰性德)","url":"/shiwenv_df44586198a8.aspx"},{"title":"寿楼春·寻春服感念","author":"寿楼春·寻春服感念(史达祖)","url":"/shiwenv_5f9786fcd621.aspx"},{"title":"书琵琶背","author":"书琵琶背(李煜)","url":"/shiwenv_1777ede28f05.aspx"},{"title":"东风齐着力·电急流光","author":"东风齐着力·电急流光(纳兰性德)","url":"/shiwenv_1cde63e6e618.aspx"},{"title":"妾薄命·为曾南丰作","author":"妾薄命·为曾南丰作(陈师道)","url":"/shiwenv_e361b50cdde6.aspx"},{"title":"悼室人","author":"悼室人(江淹)","url":"/shiwenv_9f58c0449c6e.aspx"},{"title":"思佳客·迷蝶无踪晓梦","author":"思佳客·迷蝶无踪晓梦(吴文英)","url":"/shiwenv_f483d49bf8d9.aspx"},{"title":"悼亡三首","author":"悼亡三首(梅尧臣)","url":"/shiwenv_d0875a66e2d2.aspx"},{"title":"三姝媚·过都城旧居有","author":"三姝媚·过都城旧居有(吴文英)","url":"/shiwenv_3fa4b168963d.aspx"},{"title":"六么令·夷则宫七夕","author":"六么令·夷则宫七夕(吴文英)","url":"/shiwenv_2fc22106f94d.aspx"},{"title":"望湘人·春思","author":"望湘人·春思(贺铸)","url":"/shiwenv_2a96187f4ba5.aspx"}]}]